[
  {"id": 1, "name": "Rahul Sharma", "company": "Tech Mahindra", "gender": "Male"},
  {"id": 2, "name": "Arjun Singh", "company": "Infosys", "gender": "Male"},
  {"id": 3, "name": "Naresh Kumar", "company": "Wipro", "gender": "Male"},
  {"id": 4, "name": "Suresh Reddy", "company": "TCS", "gender": "Male"},
  {"id": 5, "name": "Vikas Gupta", "company": "HCL", "gender": "Male"},
  {"id": 6, "name": "Amit Patel", "company": "Cognizant", "gender": "Male"},
  {"id": 7, "name": "Vijay Malhotra", "company": "Capgemini", "gender": "Male"},
  {"id": 8, "name": "Sunil Joshi", "company": "IBM", "gender": "Male"},
  {"id": 9, "name": "Ravi Verma", "company": "Dell", "gender": "Male"},
  {"id": 10, "name": "Rakesh Rao", "company": "Accenture", "gender": "Male"},
  {"id": 11, "name": "Rohan Desai", "company": "Microsoft", "gender": "Male"},
  {"id": 12, "name": "Nitin Mehta", "company": "Google", "gender": "Male"},
  {"id": 13, "name": "Pranav Sharma", "company": "Facebook", "gender": "Male"},
  {"id": 14, "name": "Ankit Chawla", "company": "Apple", "gender": "Male"},
  {"id": 15, "name": "Pawan Mishra", "company": "Amazon", "gender": "Male"},
  {"id": 16, "name": "Harish Rao", "company": "Oracle", "gender": "Male"},
  {"id": 17, "name": "Aditya Sinha", "company": "SAP", "gender": "Male"},
  {"id": 18, "name": "Anil Kapoor", "company": "Salesforce", "gender": "Male"},
  {"id": 19, "name": "Karan Khanna", "company": "Adobe", "gender": "Male"},
  {"id": 20, "name": "Rishi Aggarwal", "company": "VMware", "gender": "Male"},
  {"id": 21, "name": "Deepak Jain", "company": "Intel", "gender": "Male"},
  {"id": 22, "name": "Vivek Dubey", "company": "Cisco", "gender": "Male"},
  {"id": 23, "name": "Ashish Goel", "company": "HP", "gender": "Male"},
  {"id": 24, "name": "Rajesh Singh", "company": "LG", "gender": "Male"},
  {"id": 25, "name": "Sanjay Chauhan", "company": "Samsung", "gender": "Male"},
  {"id": 26, "name": "Manoj Pandey", "company": "Sony", "gender": "Male"},
  {"id": 27, "name": "Arvind Agarwal", "company": "Nokia", "gender": "Male"},
  {"id": 28, "name": "Vimal Bhatt", "company": "OnePlus", "gender": "Male"},
  {"id": 29, "name": "Himanshu Gupta", "company": "Xiaomi", "gender": "Male"},
  {"id": 30, "name": "Raghu Ram", "company": "Oppo", "gender": "Male"},
  {"id": 31, "name": "Rajiv Kumar", "company": "Vivo", "gender": "Male"},
  {"id": 32, "name": "Sagar Mehta", "company": "Asus", "gender": "Male"},
  {"id": 33, "name": "Mohit Jain", "company": "Huawei", "gender": "Male"},
  {"id": 34, "name": "Gaurav Sharma", "company": "Motorola", "gender": "Male"},
  {"id": 35, "name": "Tarun Sharma", "company": "HTC", "gender": "Male"},
  {"id": 36, "name": "Yash Singh", "company": "LG", "gender": "Male"},
  {"id": 37, "name": "Ankur Mehta", "company": "Micromax", "gender": "Male"},
  {"id": 38, "name": "Ritesh Patel", "company": "Karbonn", "gender": "Male"},
  {"id": 39, "name": "Naveen Kumar", "company": "Lava", "gender": "Male"},
  {"id": 40, "name": "Prateek Soni", "company": "Intex", "gender": "Male"},
  {"id": 41, "name": "Varun Joshi", "company": "Reliance", "gender": "Male"},
  {"id": 42, "name": "Shashank Reddy", "company": "Paytm", "gender": "Male"},
  {"id": 43, "name": "Kunal Thakur", "company": "Flipkart", "gender": "Male"},
  {"id": 44, "name": "Rahul Yadav", "company": "Snapdeal", "gender": "Male"},
  {"id": 45, "name": "Aman Agarwal", "company": "OLA", "gender": "Male"},
  {"id": 46, "name": "Raghav Kapoor", "company": "Uber", "gender": "Male"},
  {"id": 47, "name": "Ashok Verma", "company": "Zomato", "gender": "Male"},
  {"id": 48, "name": "Rajat Sharma", "company": "Swiggy", "gender": "Male"},
  {"id": 49, "name": "Ajay Sharma", "company": "BYJU's", "gender": "Male"},
  {"id": 50, "name": "Abhinav Sharma", "company": "Unacademy", "gender": "Male"},
  {"id": 51, "name": "Priya Singh", "company": "Infosys", "gender": "Female"},
  {"id": 52, "name": "Neha Verma", "company": "Wipro", "gender": "Female"},
  {"id": 53, "name": "Sneha Gupta", "company": "TCS", "gender": "Female"},
  {"id": 54, "name": "Divya Patel", "company": "HCL", "gender": "Female"},
  {"id": 55, "name": "Ananya Reddy", "company": "Cognizant", "gender": "Female"},
  {"id": 56, "name": "Pooja Malhotra", "company": "Capgemini", "gender": "Female"},
  {"id": 57, "name": "Isha Joshi", "company": "IBM", "gender": "Female"},
  {"id": 58, "name": "Sakshi Verma", "company": "Dell", "gender": "Female"},
  {"id": 59, "name": "Tanvi Rao", "company": "Accenture", "gender": "Female"},
  {"id": 60, "name": "Neha Desai", "company": "Microsoft", "gender": "Female"},
  {"id": 61, "name": "Riya Mehta", "company": "Google", "gender": "Female"},
  {"id": 62, "name": "Simran Sharma", "company": "Facebook", "gender": "Female"},
  {"id": 63, "name": "Khushi Chawla", "company": "Apple", "gender": "Female"},
  {"id": 64, "name": "Alisha Mishra", "company": "Amazon", "gender": "Female"},
  {"id": 65, "name": "Anjali Rao", "company": "Oracle", "gender": "Female"},
  {"id": 66, "name": "Priyanka Sinha", "company": "SAP", "gender": "Female"},
  {"id": 67, "name": "Komal Kapoor", "company": "Salesforce", "gender": "Female"},
  {"id": 68, "name": "Shreya Khanna", "company": "Adobe", "gender": "Female"},
  {"id": 69, "name": "Aditi Aggarwal", "company": "VMware", "gender": "Female"},
  {"id": 70, "name": "Sneha Jain", "company": "Intel", "gender":"Female"},
  {"id": 71, "name": "Ankita Dubey", "company": "Cisco", "gender":"Female"}
]